{
  "version": 3,
  "middleware": {
    "/": {
      "files": [
        "server/edge-runtime-webpack.js",
        "server/middleware.js"
      ],
      "name": "middleware",
      "page": "/",
      "matchers": [
        {
          "regexp": "^(?:\\/(_next\\/data\\/[^/]{1,}))?(?:\\/((?!api|_next|.*\\..*).*))(.json)?[\\/#\\?]?$",
          "originalSource": "/((?!api|_next|.*\\..*).*)"
        }
      ],
      "wasm": [],
      "assets": [],
      "env": {
        "__NEXT_BUILD_ID": "lkKqmwQYLI1nRheMMK8fg",
        "NEXT_SERVER_ACTIONS_ENCRYPTION_KEY": "BEHqqi6qGLBnshr3K/1Ko9LNe4Ue9fbb6DsoQOWbR+k=",
        "__NEXT_PREVIEW_MODE_ID": "c72d0cb22ab7a8a9fde98d718757dac2",
        "__NEXT_PREVIEW_MODE_ENCRYPTION_KEY": "4037c652e7f3bfea4487db219a69eb3d08c861e7611de7f913d15a91347313c9",
        "__NEXT_PREVIEW_MODE_SIGNING_KEY": "38cd840f2e15046cd942b79e8c852281195eb1d9d7ee4ed9709d55f26f17441c"
      }
    }
  },
  "functions": {},
  "sortedMiddleware": [
    "/"
  ]
}